{
  "_meta": {
    "compiled": "2026-04-22",
    "note": "台股熱門主題板塊，每季建議人工更新一次。名單來自 StockFeel、商周、Sinotrade、Anue、money.udn、Yahoo TW 等公開財經媒體整理。",
    "update_instructions": "增刪主題或調整成分股時，直接編輯本檔案即可。"
  },
  "themes": {
    "CPO_矽光子": {
      "name_zh": "CPO / 矽光子",
      "name_en": "CPO / Silicon Photonics",
      "stocks": ["2330", "3711", "2345", "2455", "3081", "3163", "3363", "3450", "4977", "4979", "4971"]
    },
    "AI伺服器": {
      "name_zh": "AI伺服器",
      "name_en": "AI Server",
      "stocks": ["2317", "2382", "3231", "6669", "2356", "2357", "2376", "5274", "3533", "8210", "3693", "2308", "2301", "2385", "4966", "5269"]
    },
    "先進封裝_CoWoS": {
      "name_zh": "先進封裝 / CoWoS",
      "name_en": "Advanced Packaging / CoWoS",
      "stocks": ["2330", "3711", "2449", "3583", "3131", "6187", "2464", "5443", "6640", "3189", "8046", "3037"]
    },
    "HBM記憶體": {
      "name_zh": "HBM記憶體",
      "name_en": "HBM / High Bandwidth Memory",
      "stocks": ["2408", "3260", "8299", "2344", "2337", "4967", "6770", "3006", "8271"]
    },
    "液冷散熱": {
      "name_zh": "液冷散熱",
      "name_en": "Liquid Cooling / Thermal",
      "stocks": ["3324", "3017", "6805", "8996", "3483", "6125", "2486", "6230", "3652"]
    },
    "重電_電網": {
      "name_zh": "重電 / 電網",
      "name_en": "Heavy Electrical / Power Grid",
      "stocks": ["1519", "1513", "1503", "1514", "2371", "1504", "1605", "1609", "1608", "6282", "2308"]
    },
    "軍工": {
      "name_zh": "軍工",
      "name_en": "Defense / Aerospace",
      "stocks": ["2634", "8033", "2630", "2645", "4541", "8222", "6829", "2208", "6753", "4536", "1584"]
    },
    "機器人": {
      "name_zh": "機器人",
      "name_en": "Robotics",
      "stocks": ["2308", "2049", "1597", "4540", "2395", "6166", "2464", "1504", "1503", "2359", "3088", "2360"]
    },
    "無人機": {
      "name_zh": "無人機",
      "name_en": "Drone / UAV",
      "stocks": ["2634", "8033", "5371", "2645", "2630", "4541", "3437", "6829", "8495", "3416", "2231"]
    },
    "鋰電池_儲能": {
      "name_zh": "鋰電池 / 儲能",
      "name_en": "Lithium Battery / Energy Storage",
      "stocks": ["6121", "3211", "3323", "1729", "2308", "1513", "1514", "1519", "6806", "6873"]
    },
    "PCB_ABF": {
      "name_zh": "PCB / ABF載板",
      "name_en": "PCB / ABF Substrate",
      "stocks": ["3037", "3189", "8046", "3044", "2313", "4958", "6269", "2383", "6213", "6274", "2368", "3013"]
    },
    "矽智財_IP": {
      "name_zh": "矽智財 / IP設計",
      "name_en": "Silicon IP / IC Design IP",
      "stocks": ["3443", "3661", "6533", "3529", "6643", "3035", "6568"]
    },
    "低軌衛星": {
      "name_zh": "低軌衛星",
      "name_en": "LEO Satellite",
      "stocks": ["3491", "2314", "2313", "6285", "2383", "7717", "2485", "6271", "3305", "3178"]
    },
    "CXO_生技代工": {
      "name_zh": "CXO / 生技代工",
      "name_en": "CDMO / Biotech Contract Mfg",
      "stocks": ["6472", "6589", "6446", "4162", "4174", "6905"]
    },
    "網通_5G": {
      "name_zh": "網通 / 5G",
      "name_en": "Networking / 5G",
      "stocks": ["2345", "5388", "6285", "3380", "3704", "3596", "3491", "2454", "4919", "2379"]
    },
    "ADAS_智駕": {
      "name_zh": "ADAS / 智駕",
      "name_en": "ADAS / Autonomous Driving",
      "stocks": ["1533", "2497", "2231", "3227", "3552", "1521", "2401", "3346", "6283", "8255", "2436", "3059"]
    },
    "綠能_太陽能": {
      "name_zh": "綠能 / 太陽能",
      "name_en": "Green Energy / Solar",
      "stocks": ["6443", "6244", "3576", "6477", "6806", "6873", "2308", "1513"]
    },
    "蘋果概念": {
      "name_zh": "蘋果概念",
      "name_en": "Apple Supply Chain",
      "stocks": ["2330", "3008", "2317", "4938", "2474", "2354", "3711", "6269", "3673", "3105", "4958", "8086"]
    },
    "車用電子": {
      "name_zh": "車用電子",
      "name_en": "Automotive Electronics",
      "stocks": ["2308", "3665", "1319", "2231", "2497", "1533", "3552", "2328", "2436", "1504"]
    },
    "被動元件": {
      "name_zh": "被動元件",
      "name_en": "Passive Components",
      "stocks": ["2327", "2492", "3026", "6173", "2456", "2308", "5425"]
    },
    "Edge_AI": {
      "name_zh": "Edge AI",
      "name_en": "Edge AI / On-device AI",
      "stocks": ["2454", "2379", "3014", "2436", "6669", "8234", "2395", "6166", "4919", "5274"]
    },
    "折疊螢幕": {
      "name_zh": "折疊螢幕",
      "name_en": "Foldable Display",
      "stocks": ["3673", "3376", "3548", "6805", "2409", "3481"]
    },
    "電動車_EV": {
      "name_zh": "電動車 / EV",
      "name_en": "Electric Vehicle",
      "stocks": ["2308", "2317", "1536", "1319", "3665", "1504", "2301", "6282", "6714", "6121"]
    },
    "半導體設備": {
      "name_zh": "半導體設備",
      "name_en": "Semiconductor Equipment",
      "stocks": ["3131", "3583", "2404", "6196", "5536", "6691", "5443", "6187"]
    },
    "光學鏡頭": {
      "name_zh": "光學鏡頭",
      "name_en": "Optical Lens / Camera",
      "stocks": ["3008", "3406", "3019", "3362", "2374", "5371"]
    }
  }
}
